Metadata-Version: 2.4
Name: pydra-tasks-dcm2niix
Version: 1.4
Summary: pydra-tasks-dcm2niix contains Pydra task specifications for the Dcm2niix converter
Author-email: "Thomas G. Close" <tom.g.close@gmail.com>
Maintainer-email: "Thomas G. Close" <tom.g.close@gmail.com>
License:    Copyright 2021 Nipype developers
License-File: LICENSE
Keywords: pydra
Classifier: Development Status :: 2 - Pre-Alpha
Classifier: Environment :: Console
Classifier: Intended Audience :: Science/Research
Classifier: License :: OSI Approved :: Apache Software License
Classifier: Operating System :: MacOS :: MacOS X
Classifier: Operating System :: POSIX :: Linux
Classifier: Programming Language :: Python :: 3
Classifier: Topic :: Scientific/Engineering
Requires-Python: >=3.11
Requires-Dist: fileformats-medimage>=0.10a
Requires-Dist: fileformats>=0.15
Requires-Dist: pydra>=1.0a
Provides-Extra: dev
Requires-Dist: attrs>=23.1.0; extra == 'dev'
Requires-Dist: black; extra == 'dev'
Requires-Dist: black>=22.12.0; extra == 'dev'
Requires-Dist: click>=8.1.3; extra == 'dev'
Requires-Dist: fileformats-extras>=0.15a2; extra == 'dev'
Requires-Dist: pre-commit; extra == 'dev'
Requires-Dist: tqdm; extra == 'dev'
Provides-Extra: doc
Requires-Dist: packaging; extra == 'doc'
Requires-Dist: sphinx-rtd-theme; extra == 'doc'
Requires-Dist: sphinx>=2.1.2; extra == 'doc'
Requires-Dist: sphinxcontrib-apidoc~=0.3.0; extra == 'doc'
Requires-Dist: sphinxcontrib-napoleon; extra == 'doc'
Requires-Dist: sphinxcontrib-versioning; extra == 'doc'
Provides-Extra: test
Requires-Dist: codecov; extra == 'test'
Requires-Dist: pytest-cov; extra == 'test'
Requires-Dist: pytest-env; extra == 'test'
Requires-Dist: pytest-rerunfailures; extra == 'test'
Requires-Dist: pytest-xdist; extra == 'test'
Requires-Dist: pytest>=4.4.0; extra == 'test'
